{
    "cgroup": {
        "cpu": {
            "shares": 128,
            "cfs_limit": 0.05,
            "rt_limit": 0.80,
            "clone_children": 1,
            "sane_behavior": 1
        },
        "cpuset": {
            "cpus": "0-1,4",
            "load_balance": 0,
            "cpu_exclusive": 1
        },
        "memory": {
            "memory_limit": "64M",
            "tcp_kmemory_limit": "1G"
        },
        "cpuacct": {
            "enable": 1
        }
    },
    "namespace": {

    },
    "test": "Hello World!\n"
}